odoo8_addon_hr_holidays_compute_days-8.0.1.0.0.99.dev6-py2.7-nspkg.pth
odoo8_addon_hr_holidays_compute_days-8.0.1.0.0.99.dev6.dist-info/DESCRIPTION.rst
odoo8_addon_hr_holidays_compute_days-8.0.1.0.0.99.dev6.dist-info/METADATA
odoo8_addon_hr_holidays_compute_days-8.0.1.0.0.99.dev6.dist-info/RECORD
odoo8_addon_hr_holidays_compute_days-8.0.1.0.0.99.dev6.dist-info/WHEEL
odoo8_addon_hr_holidays_compute_days-8.0.1.0.0.99.dev6.dist-info/metadata.json
odoo8_addon_hr_holidays_compute_days-8.0.1.0.0.99.dev6.dist-info/namespace_packages.txt
odoo8_addon_hr_holidays_compute_days-8.0.1.0.0.99.dev6.dist-info/top_level.txt
odoo_addons/hr_holidays_compute_days/README.rst
odoo_addons/hr_holidays_compute_days/__init__.py
odoo_addons/hr_holidays_compute_days/__openerp__.py
odoo_addons/hr_holidays_compute_days/i18n/ar.po
odoo_addons/hr_holidays_compute_days/i18n/de.po
odoo_addons/hr_holidays_compute_days/i18n/es.po
odoo_addons/hr_holidays_compute_days/i18n/fi.po
odoo_addons/hr_holidays_compute_days/i18n/fr.po
odoo_addons/hr_holidays_compute_days/i18n/hr_holidays_compute_days.pot
odoo_addons/hr_holidays_compute_days/i18n/it.po
odoo_addons/hr_holidays_compute_days/i18n/nl.po
odoo_addons/hr_holidays_compute_days/i18n/nl_NL.po
odoo_addons/hr_holidays_compute_days/i18n/pt_BR.po
odoo_addons/hr_holidays_compute_days/i18n/ro.po
odoo_addons/hr_holidays_compute_days/i18n/sl.po
odoo_addons/hr_holidays_compute_days/models/__init__.py
odoo_addons/hr_holidays_compute_days/models/hr_employee.py
odoo_addons/hr_holidays_compute_days/models/hr_holidays.py
odoo_addons/hr_holidays_compute_days/models/hr_holidays_status.py
odoo_addons/hr_holidays_compute_days/security/ir.model.access.csv
odoo_addons/hr_holidays_compute_days/security/ir_rule.xml
odoo_addons/hr_holidays_compute_days/static/description/icon.png
odoo_addons/hr_holidays_compute_days/tests/__init__.py
odoo_addons/hr_holidays_compute_days/tests/test_holidays_compute_days.py
odoo_addons/hr_holidays_compute_days/views/hr_holidays_status.xml
odoo_addons/hr_holidays_compute_days/views/hr_holidays_view.xml
